README.rst
setup.py
slinker/__init__.py
slinker/dispatcher.py
slinker/saferef.py
slinker.egg-info/PKG-INFO
slinker.egg-info/SOURCES.txt
slinker.egg-info/dependency_links.txt
slinker.egg-info/top_level.txt