Metadata-Version: 1.1
Name: slinker
Version: 0.1
Summary: A signal one to one event
Home-page: http://www.flyzen.com
Author: Young King
Author-email: jek@discorporate.us
License: MIT License
Keywords: signal event emit rpc
Platform: UNKNOWN
Classifier: Development Status :: 5 - Production/Stable
Classifier: Intended Audience :: Developers
Classifier: License :: OSI Approved :: MIT License
Classifier: Operating System :: OS Independent
Classifier: Programming Language :: Python
Classifier: Programming Language :: Python :: 2.7
Classifier: Topic :: Software Development :: Libraries
Classifier: Topic :: Utilities
